hero_selection_component/__init__.py
hero_selection_component/example.py
hero_selection_component/streamlit_callback.py
hero_selection_component/frontend/build/asset-manifest.json
hero_selection_component/frontend/build/bootstrap.min.css
hero_selection_component/frontend/build/bootstrap.min.css.map
hero_selection_component/frontend/build/index.html
hero_selection_component/frontend/build/static/css/main.59984f40.css
hero_selection_component/frontend/build/static/css/main.59984f40.css.map
hero_selection_component/frontend/build/static/js/main.8a1a9069.js
hero_selection_component/frontend/build/static/js/main.8a1a9069.js.LICENSE.txt
hero_selection_component/frontend/build/static/js/main.8a1a9069.js.map
hero_selection-0.0.7.dist-info/LICENSE
hero_selection-0.0.7.dist-info/METADATA
hero_selection-0.0.7.dist-info/WHEEL
hero_selection-0.0.7.dist-info/top_level.txt
hero_selection-0.0.7.dist-info/RECORD
